[
  {
    "name": "Concatenate (smoosh) strings",
    "answer": "'foobar'",
    "correct": true,
    "timestamp": 1661378271635
  },
  {
    "name": "Indexing",
    "answer": "false",
    "correct": false,
    "timestamp": 1661378431135
  },
  {
    "name": "Indexing",
    "answer": "'false'",
    "correct": false,
    "timestamp": 1661378474192
  },
  {
    "name": "Indexing",
    "answer": "'f'",
    "correct": true,
    "timestamp": 1661378478032
  },
  {
    "name": "Length",
    "answer": "3",
    "correct": true,
    "timestamp": 1661378488448
  },
  {
    "name": "Another length",
    "answer": "7",
    "correct": true,
    "timestamp": 1661378493512
  },
  {
    "name": "And one more",
    "answer": "8",
    "correct": true,
    "timestamp": 1661378496920
  },
  {
    "name": "More indexing",
    "answer": "k",
    "correct": false,
    "timestamp": 1661378531745
  },
  {
    "name": "More indexing",
    "answer": "12",
    "correct": false,
    "timestamp": 1661378637780
  },
  {
    "name": "More indexing",
    "answer": "o",
    "correct": false,
    "timestamp": 1661378688527
  },
  {
    "name": "More indexing",
    "answer": "2",
    "correct": false,
    "timestamp": 1661378691871
  },
  {
    "name": "More indexing",
    "answer": "'2'",
    "correct": false,
    "timestamp": 1661378711024
  },
  {
    "name": "More indexing",
    "answer": "'o'",
    "correct": true,
    "timestamp": 1661378889782
  },
  {
    "name": "UPPER CASE",
    "answer": "'Foo'",
    "correct": false,
    "timestamp": 1661379472583
  },
  {
    "name": "UPPER CASE",
    "answer": "'FOO'",
    "correct": true,
    "timestamp": 1661379476055
  },
  {
    "name": "lower case",
    "answer": "'foo'",
    "correct": true,
    "timestamp": 1661379482392
  },
  {
    "name": "First character",
    "answer": "s.substring(0,1)",
    "correct": true,
    "timestamp": 1661379541851
  },
  {
    "name": "All but first",
    "answer": "s.substring(1)",
    "correct": true,
    "timestamp": 1661379657438
  },
  {
    "name": "First three",
    "answer": "s.substring(0,3)",
    "correct": true,
    "timestamp": 1661379667790
  },
  {
    "name": "Concatenate (smoosh) strings",
    "answer": "s.substring(0,0)",
    "correct": false,
    "timestamp": 1661379707028
  }
]